summit/__init__.py
summit/benchmarks/MIT/MIT_kin_case1.py
summit/benchmarks/MIT/MIT_kin_case2.py
summit/benchmarks/MIT/MIT_kin_case3.py
summit/benchmarks/MIT/MIT_kin_case4.py
summit/benchmarks/MIT/MIT_kin_case5.py
summit/benchmarks/MIT/__init__.py
summit/benchmarks/__init__.py
summit/benchmarks/data/README.md
summit/benchmarks/data/baumgartenter_benzamide_cross_coupling.csv
summit/benchmarks/data/baumgartner_aniline_cn_crosscoupling.csv
summit/benchmarks/data/reizman_suzuki_case_1.csv
summit/benchmarks/data/reizman_suzuki_case_2.csv
summit/benchmarks/data/reizman_suzuki_case_3.csv
summit/benchmarks/data/reizman_suzuki_case_4.csv
summit/benchmarks/experimental_emulator.py
summit/benchmarks/models/baumgartner_aniline_cn_crosscoupling/baumgartner_aniline_cn_crosscoupling.json
summit/benchmarks/models/baumgartner_aniline_cn_crosscoupling/baumgartner_aniline_cn_crosscoupling_predictor_0.pt
summit/benchmarks/models/baumgartner_aniline_cn_crosscoupling/baumgartner_aniline_cn_crosscoupling_predictor_1.pt
summit/benchmarks/models/baumgartner_aniline_cn_crosscoupling/baumgartner_aniline_cn_crosscoupling_predictor_2.pt
summit/benchmarks/models/baumgartner_aniline_cn_crosscoupling/baumgartner_aniline_cn_crosscoupling_predictor_3.pt
summit/benchmarks/models/baumgartner_aniline_cn_crosscoupling/baumgartner_aniline_cn_crosscoupling_predictor_4.pt
summit/benchmarks/models/baumgartner_aniline_cn_crosscoupling_descriptors/baumgartner_aniline_cn_crosscoupling_descriptors.json
summit/benchmarks/models/baumgartner_aniline_cn_crosscoupling_descriptors/baumgartner_aniline_cn_crosscoupling_descriptors_predictor_0.pt
summit/benchmarks/models/baumgartner_aniline_cn_crosscoupling_descriptors/baumgartner_aniline_cn_crosscoupling_descriptors_predictor_1.pt
summit/benchmarks/models/baumgartner_aniline_cn_crosscoupling_descriptors/baumgartner_aniline_cn_crosscoupling_descriptors_predictor_2.pt
summit-0.8.9.dist-info/entry_points.txt
summit-0.8.9.dist-info/LICENSE
summit-0.8.9.dist-info/WHEEL
summit-0.8.9.dist-info/METADATA
summit-0.8.9.dist-info/RECORD
