Metadata-Version: 2.1
Name: summit
Version: 0.8.9
Summary: Tools for optimizing chemical processes
Home-page: https://github.com/sustainable-processes/summit
License: MIT
Keywords: machine-learning,chemistry,bayesian-reaction-optimization,reaction-optimization,neural-networks,process optimization,bayesian-optimization,nelder-mead,snobfit,gryffin,TSEMO
Author: Kobi Felton
Author-email: kobi.c.f@gmail.com
Requires-Python: >=3.8,<3.11
Classifier: License :: OSI Approved :: MIT License
Classifier: Programming Language :: Python :: 3
Classifier: Programming Language :: Python :: 3.8
Classifier: Programming Language :: Python :: 3.9
Classifier: Programming Language :: Python :: 3.10
Provides-Extra: bnn
Provides-Extra: docs
Provides-Extra: entmoot
Provides-Extra: experiments
Requires-Dist: GPy (>=1.9,<2.0)
Requires-Dist: SQSnobFit (>=0.4.3,<0.5.0)
Requires-Dist: botorch (>=0.8.0,<0.9.0)
Requires-Dist: cython (>=0.29.21,<0.30.0)
Requires-Dist: entmoot (>=0.1.4,<0.2.0); extra == "entmoot"
Requires-Dist: fastprogress (>=0.2.3,<0.3.0)
Requires-Dist: gpyopt (>=1.2.6,<2.0.0)
Requires-Dist: hiplot (>=0.1.12,<0.2.0); extra == "experiments"
Requires-Dist: jinja2 (<3.1.0); extra == "docs"
Requires-Dist: llvmlite (>=0.38.0,<0.39.0)
Requires-Dist: matplotlib (>=3.2.2,<4.0.0)
Requires-Dist: nbsphinx (>=0.8.5,<0.9.0); extra == "docs"
Requires-Dist: neptune-client (>=0.4.115,<0.5.0); extra == "experiments"
Requires-Dist: numba (>=0.55.0,<0.56.0)
Requires-Dist: numpy (>=1.21.0,<2.0.0)
Requires-Dist: pandas (>=1.1.0,<2.0.0)
Requires-Dist: paramiko (>=2.7.1,<3.0.0); extra == "experiments"
Requires-Dist: pymoo (>=0.6.0,<0.7.0)
Requires-Dist: pyrecorder (>=0.1.8,<0.2.0); extra == "experiments"
Requires-Dist: pyrff (>=2.0.1,<3.0.0)
Requires-Dist: pytest (>=6.2.5,<7.0.0)
Requires-Dist: scikit-learn (>=1.0,<2.0)
Requires-Dist: scipy (>=1.8.0)
Requires-Dist: skorch (>=0.11.0,<0.12.0)
Requires-Dist: sphinx (>=3.2.1,<4.0.0); extra == "docs"
Requires-Dist: sphinx-reredirects (>=0.0.0,<0.0.1); extra == "docs"
Requires-Dist: sphinx-rtd-theme (>=0.5.0,<0.6.0); extra == "docs"
Requires-Dist: streamlit (>=0.67.1,<1.12.0); extra == "experiments"
Requires-Dist: torch (>=1.11.0,<2.0.0)
Requires-Dist: xlrd (>=1.2.0,<2.0.0); extra == "experiments"
Project-URL: Repository, https://github.com/sustainable-processes/summit
